libpuz/__init__.py
libpuz/example/__init__.py
libpuz/example/example.py
libpuz/nonogram/example.columns.csv
libpuz/nonogram/example.json
libpuz/nonogram/example.rows.csv
libpuz/nonogram/nonogram
libpuz/tst/__init__.py
libpuz/tst/example/__init__.py
libpuz/tst/example/example-test.py
libpuz-0.3.data/scripts/nonogram
libpuz-0.3.dist-info/DESCRIPTION.rst
libpuz-0.3.dist-info/METADATA
libpuz-0.3.dist-info/RECORD
libpuz-0.3.dist-info/WHEEL
libpuz-0.3.dist-info/metadata.json
libpuz-0.3.dist-info/top_level.txt
